LICENSE.txt
MANIFEST.in
setup.py
abl/__init__.py
abl.jquery.plugins.form.egg-info/PKG-INFO
abl.jquery.plugins.form.egg-info/SOURCES.txt
abl.jquery.plugins.form.egg-info/dependency_links.txt
abl.jquery.plugins.form.egg-info/entry_points.txt
abl.jquery.plugins.form.egg-info/namespace_packages.txt
abl.jquery.plugins.form.egg-info/not-zip-safe
abl.jquery.plugins.form.egg-info/requires.txt
abl.jquery.plugins.form.egg-info/top_level.txt
abl/jquery/__init__.py
abl/jquery/examples/__init__.py
abl/jquery/examples/form/__init__.py
abl/jquery/examples/form/base.py
abl/jquery/examples/form/templates/__init__.py
abl/jquery/plugins/__init__.py
abl/jquery/plugins/form/__init__.py
abl/jquery/plugins/form/resources.py
abl/jquery/plugins/form/widgets.py
abl/jquery/plugins/form/static/css/form_widget.css
abl/jquery/plugins/form/static/css/images/ajax-loader.gif
abl/jquery/plugins/form/static/javascript/jquery.form.js
abl/jquery/plugins/form/static/javascript/jquery.form.widget.js
abl/jquery/plugins/form/templates/__init__.py