Metadata-Version: 1.0
Name: abl.jquery.plugins.form
Version: 2.49
Summary: ToscaWidgets wrapper for jquery.form.js
Home-page: UNKNOWN
Author: Diez B. Roggisch
Author-email: deets@web.de
License: MIT
Keywords: toscawidgets.widgets
Platform: UNKNOWN
